libname/__init__.py
libname/addition.py
pialgebra-0.0.1.dist-info/LICENSE
pialgebra-0.0.1.dist-info/METADATA
pialgebra-0.0.1.dist-info/WHEEL
pialgebra-0.0.1.dist-info/top_level.txt
pialgebra-0.0.1.dist-info/RECORD
