Metadata-Version: 2.1
Name: pialgebra
Version: 0.0.1
Summary: Lorem ipsum...
Author: Pierre
Author-email: pierre.bejian@gmail.com
License-File: LICENSE
Requires-Dist: numpy
